[
  {
    "name": "Grassland",
    "color": "#3e502a",
    "minHeight": 0.10,
    "maxHeight": 0.20,
    "minTemp": 0.3,
    "maxTemp": 1.0,
    "minMoisture": 0.2,
    "maxMoisture": 0.6
  },
  {
    "name": "Woodland",
    "color": "#33501d",
    "minHeight": 0.20,
    "maxHeight": 0.35,
    "minTemp": 0.4,
    "maxTemp": 0.8,
    "minMoisture": 0.7,
    "maxMoisture": 1.0
  },
  {
    "name": "Forest",
    "color": "#293c13",
    "minHeight": 0.20,
    "maxHeight": 0.70,
    "minTemp": 0.4,
    "maxTemp": 1.0,
    "minMoisture": 0.4,
    "maxMoisture": 1.0
  },
  {
    "name": "Hills",
    "color": "#383d30",
    "minHeight": 0.70,
    "maxHeight": 0.80,
    "minTemp": 0.3,
    "maxTemp": 0.8,
    "minMoisture": 0.2,
    "maxMoisture": 0.6
  },
  {
    "name": "Mountains",
    "color": "#484E3F",
    "minHeight": 0.80,
    "maxHeight": 1.0,
    "minTemp": 0.0,
    "maxTemp": 0.6,
    "minMoisture": 0.0,
    "maxMoisture": 0.6
  }
]
